[
  {
    "id": "Build-by-L-Malakar",
    "name": "Build by L. Malakar",
    "altName": "Developer L. Malakar",
    "image": "https://lemystore.web.app/dev/L.%20Malakar.jpeg",
    "genre": [
      "Developer",
      "Builder",
      "AI use"
    ],
    "date": "2026-06",
    "season": "Blog",
    "language": "English",
    "link": "https://www.youtube.com/@gdmalakar",
    "videoUrl": "https://lemystore.web.app",
    "seasons": [
      "Blog"
    ],
    "episodeLinks": {
      "s1": {
        "e1": "https://lemystore.web.app/video/Paper%20Plain.mp4",
        "e2": "https://lemystore.web.app/video/LE%20Chess.mp4"
      }
    },
    "details": "https://www.instagram.com/devxmalakar/",
    "state": "watched",
    "sst": "top_life",
    "rank": 1,
    "rating": 10,
    "tear": "SSS",
    "episodes": 2,
    "studio": "L. Malakar",
    "year": 2026,
    "review": "This is a demo of how a striming platfrom work, and you are free to use this codes on your own striming platfrom.",
    "tags": [
      "Dev",
      "Yt",
      "SSS+"
    ]
  },
]
